[
    {
      "name": "Hossein Toreyhi",
      "contributedTo": ["Project Administration", "Conceptualization", "Methodology", "Writing - Original Draft"],
      "email": "hoseinto@gmail.com",
      "affiliation": "Research Institute for Gastroenterology and Liver Diseases, SBMU, Tehran, Iran",
      "image": ""
    },
    {
        "name": "Seyed Amir Ahmad Safavi Naini",
        "contributedTo": ["Project Administration", "Funding Acquisition",  "Conceptualization", "Supervision", "Writing - Review & Editing"],
        "email": "sdamirsa@ymail.com",
        "affiliation": "Research Institute for Gastroenterology and Liver Diseases, SBMU, Tehran, Iran",
        "image": ""
      },
     {
        "name": "Yasamin Falahati",
        "contributedTo": ["Template_bioinformatic", "Genomic & Molecular Data"],
        "email": "falahati.yasamin@gmail.com",
        "affiliation": "Islamic Azad University, Tehran medical science",
        "image": ""
      },
      {
        "name": "Alireza Hekmati",
        "contributedTo": ["Project Administration","Genomic & Molecular Data (3 parts)","Template_bioinformatic"],
        "email": "AlirezaHekmati80@gmail.com",
        "affiliation": "North Khorasan University of Medical Sciences, Bojnurd, Iran",
        "image": ""
      },
     {
        "name": "Amirhossein Nikfarjam",
        "contributedTo": ["Vid_Laryngoscopy","Vid_Bronchoscopy","Vid_Cystoscopy","Vid_Hysteroscopy"],
        "email": "niiik.2001.amir@gmail.com",
        "affiliation": "Student Research Committee, Bushehr University of Medical Sciences, Bushehr, Iran ",
        "image": ""
      },
     {
        "name": "Pooya Eini",
        "contributedTo": ["MRI standard", "Diffusion MRI (DWI/DTI)",  "Magnetic Resonance Angiography (MRA)", "Magnetic Resonance Spectroscopy (MRS)", "3D & 4D Ultrasound", "US elastography", "Writing"],
        "email": "pooyaeini.pe@gmail.com",
        "affiliation": "Excellence Center of Clinical Toxicology, Loghman Hakim Hospital, Shahid Beheshti University of Medical Sciences, Tehran, Iran",
        "image": ""
      }
    {
        "name": "Rana Hashemi",
        "contributedTo": ["fMRI", "Breast MRI",  "Cardiac MRI", "Magnetic Resonance Urography", "Magnetic Resonance Myelography", "Writing related modalities manuscript"],
        "email": "ranahashemi@yahoo.com",
        "affiliation": "Shahid Beheshti University of Medical Sciences, Tehran, Iran",
        "image": ""
      },
    {
      "name": "Arman Gharehbaghi",
      "contributedTo": ["CT_CTP", "CT_CBCT", "CT_Colonography", "Dental_OPG", "Dental_CBCT", "Dental_CR", "Writing related modalities manuscript"],
      "email": "armangharehbaghi2003@gmail.com",
      "affiliation": "Student Research Committee, Urmia University of Medical Sciences, Urmia, IRAN",
      "image": ""
    },
    {
      "name": "Shahrzad Shahrokhi Nejad",
      "contributedTo": ["Cephalometric Radiography", "CT_Conventional", "CT_HRCT", "CT_LDCT", "CT_CTA", "CT_DECT", "CT_4D CT"],
      "email": "shery.1375.sh@gmail.com",
      "affiliation": "Shahid Beheshti University of Medical Sciences, Tehran, Iran",
      "image": ""
    }
    {
      "name": "Negin Fathi Hafshejani",
      "contributedTo": ["XRay_DR", "XRay_CR", "Mammography", "B-mode (2D Ultrasound)", "Transcranial Doppler (TCD)", " Intravascular Ultrasound (IVUS)"],
      "email": "neginfathi80@gmail.com",
      "affiliation": "Student Research Committee, School of Medicine, Alborz University of Medical Sciences, Karaj, Iran",
      "image": ""
    }
  ]
